{"fastest": [{"Driver": "HAM", "LapTime": 89.033, "Diff": 0.0, "Team": "Mercedes"}, {"Driver": "BOT", "LapTime": 89.482, "Diff": 0.449, "Team": "Mercedes"}, {"Driver": "PER", "LapTime": 90.0, "Diff": 0.967, "Team": "Racing Point"}, {"Driver": "SAI", "LapTime": 90.018, "Diff": 0.985, "Team": "McLaren"}, {"Driver": "GAS", "LapTime": 90.049, "Diff": 1.016, "Team": "AlphaTauri"}, {"Driver": "VER", "LapTime": 90.294, "Diff": 1.261, "Team": "Red Bull Racing"}, {"Driver": "ALB", "LapTime": 90.302, "Diff": 1.269, "Team": "Red Bull Racing"}, {"Driver": "OCO", "LapTime": 90.384, "Diff": 1.351, "Team": "Renault"}, {"Driver": "STR", "LapTime": 90.426, "Diff": 1.393, "Team": "Racing Point"}, {"Driver": "RIC", "LapTime": 90.508, "Diff": 1.475, "Team": "Renault"}, {"Driver": "LEC", "LapTime": 90.589, "Diff": 1.556, "Team": "Ferrari"}, {"Driver": "VET", "LapTime": 90.628, "Diff": 1.595, "Team": "Ferrari"}, {"Driver": "KUB", "LapTime": 90.732, "Diff": 1.699, "Team": "Alfa Romeo Racing"}, {"Driver": "GRO", "LapTime": 90.832, "Diff": 1.799, "Team": "Haas F1 Team"}, {"Driver": "MAG", "LapTime": 90.854, "Diff": 1.821, "Team": "Haas F1 Team"}, {"Driver": "GIO", "LapTime": 90.896, "Diff": 1.863, "Team": "Alfa Romeo Racing"}, {"Driver": "KVY", "LapTime": 91.02, "Diff": 1.987, "Team": "AlphaTauri"}, {"Driver": "NOR", "LapTime": 91.392, "Diff": 2.359, "Team": "McLaren"}, {"Driver": "LAT", "LapTime": 92.472, "Diff": 3.439, "Team": "Williams"}, {"Driver": "NIS", "LapTime": 92.801, "Diff": 3.768, "Team": "Williams"}]}