{"racePace": [{"Driver": "BOT", "LapTime": 79.747, "Diff": 0.0, "Team": "Mercedes"}, {"Driver": "VER", "LapTime": 80.389, "Diff": 0.642, "Team": "Red Bull Racing"}, {"Driver": "HAM", "LapTime": 80.482, "Diff": 0.735, "Team": "Mercedes"}, {"Driver": "ALB", "LapTime": 80.499, "Diff": 0.752, "Team": "Red Bull Racing"}, {"Driver": "STR", "LapTime": 80.533, "Diff": 0.786, "Team": "Racing Point"}, {"Driver": "RIC", "LapTime": 80.582, "Diff": 0.835, "Team": "Renault"}, {"Driver": "GIO", "LapTime": 80.629, "Diff": 0.882, "Team": "Alfa Romeo Racing"}, {"Driver": "SAI", "LapTime": 80.724, "Diff": 0.977, "Team": "McLaren"}, {"Driver": "PER", "LapTime": 80.8, "Diff": 1.053, "Team": "Racing Point"}, {"Driver": "VET", "LapTime": 80.871, "Diff": 1.124, "Team": "Ferrari"}, {"Driver": "RAI", "LapTime": 80.909, "Diff": 1.162, "Team": "Alfa Romeo Racing"}, {"Driver": "MAG", "LapTime": 80.91, "Diff": 1.163, "Team": "Haas F1 Team"}, {"Driver": "RUS", "LapTime": 80.973, "Diff": 1.226, "Team": "Williams"}, {"Driver": "NOR", "LapTime": 80.986, "Diff": 1.239, "Team": "McLaren"}, {"Driver": "OCO", "LapTime": 81.047, "Diff": 1.3, "Team": "Renault"}, {"Driver": "GRO", "LapTime": 81.277, "Diff": 1.53, "Team": "Haas F1 Team"}, {"Driver": "LEC", "LapTime": 81.44, "Diff": 1.693, "Team": "Ferrari"}, {"Driver": "KVY", "LapTime": 81.501, "Diff": 1.754, "Team": "AlphaTauri"}, {"Driver": "LAT", "LapTime": 81.547, "Diff": 1.8, "Team": "Williams"}]}