{"fastest": [{"Driver": "RIC", "LapTime": 100.926, "Diff": 0.0, "Team": "Renault"}, {"Driver": "VER", "LapTime": 100.958, "Diff": 0.032, "Team": "Red Bull Racing"}, {"Driver": "BOT", "LapTime": 101.131, "Diff": 0.205, "Team": "Mercedes"}, {"Driver": "ALB", "LapTime": 101.227, "Diff": 0.301, "Team": "Red Bull Racing"}, {"Driver": "HAM", "LapTime": 101.42, "Diff": 0.494, "Team": "Mercedes"}, {"Driver": "VET", "LapTime": 101.475, "Diff": 0.549, "Team": "Ferrari"}, {"Driver": "GIO", "LapTime": 101.675, "Diff": 0.749, "Team": "Alfa Romeo Racing"}, {"Driver": "FIT", "LapTime": 101.707, "Diff": 0.781, "Team": "Haas F1 Team"}, {"Driver": "STR", "LapTime": 101.866, "Diff": 0.94, "Team": "Racing Point"}, {"Driver": "LEC", "LapTime": 101.908, "Diff": 0.982, "Team": "Ferrari"}, {"Driver": "SAI", "LapTime": 101.947, "Diff": 1.021, "Team": "McLaren"}, {"Driver": "NOR", "LapTime": 101.964, "Diff": 1.038, "Team": "McLaren"}, {"Driver": "MAG", "LapTime": 101.999, "Diff": 1.073, "Team": "Haas F1 Team"}, {"Driver": "RAI", "LapTime": 102.148, "Diff": 1.222, "Team": "Alfa Romeo Racing"}, {"Driver": "GAS", "LapTime": 102.474, "Diff": 1.548, "Team": "AlphaTauri"}, {"Driver": "LAT", "LapTime": 102.497, "Diff": 1.571, "Team": "Williams"}, {"Driver": "KVY", "LapTime": 102.704, "Diff": 1.778, "Team": "AlphaTauri"}, {"Driver": "OCO", "LapTime": 102.894, "Diff": 1.968, "Team": "Renault"}, {"Driver": "PER", "LapTime": 103.263, "Diff": 2.337, "Team": "Racing Point"}, {"Driver": "RUS", "LapTime": 103.328, "Diff": 2.402, "Team": "Williams"}]}